{
  "variants": {
    "type=north": {
      "model": "naissancee:block/white_vslab"
    },
    "type=south": {
      "model": "naissancee:block/white_vslab",
      "y": 180,
      "uvlock": true
    },
    "type=west": {
      "model": "naissancee:block/white_vslab",
      "y": 270,
      "uvlock": true
    },
    "type=east": {
      "model": "naissancee:block/white_vslab",
      "y": 90,
      "uvlock": true
    },
    "type=double": {
      "model": "naissancee:block/white_block"
    }
  }
}
